fastmindapi/__init__.py
fastmindapi/cli.py
fastmindapi/algo/__init__.py
fastmindapi/algo/tree/__init__.py
fastmindapi/algo/tree/mcts.py
fastmindapi/client/__init__.py
fastmindapi/client/core/__init__.py
fastmindapi/client/core/http_request.py
fastmindapi/client/core/main.py
fastmindapi/model/__init__.py
fastmindapi/model/inference/__init__.py
fastmindapi/model/llama_cpp/LLM.py
fastmindapi/model/llama_cpp/__init__.py
fastmindapi/model/openai/ChatModel.py
fastmindapi/model/openai/__init__.py
fastmindapi/model/transformers/CausalLM.py
fastmindapi/model/transformers/PeftModel.py
fastmindapi/model/transformers/__init__.py
fastmindapi/model/utils/__init__.py
fastmindapi/model/utils/io.py
fastmindapi/model/utils/transform.py
fastmindapi/model/vllm/LLM.py
fastmindapi/model/vllm/__init__.py
fastmindapi/modules/__init__.py
fastmindapi/modules/function/__init__.py
fastmindapi/modules/function/parser.py
fastmindapi/modules/function/pool.py
fastmindapi/modules/retrieval/__init__.py
fastmindapi/server/__init__.py
fastmindapi/server/core/__init__.py
fastmindapi/server/core/main.py
fastmindapi/server/router/__init__.py
fastmindapi/server/router/basic.py
fastmindapi/server/router/model.py
fastmindapi/server/router/openai.py
fastmindapi/types/__init__.py
fastmindapi/types/generation.py
fastmindapi/types/model.py
fastmindapi/utils/__init__.py
fastmindapi/utils/config.py
fastmindapi/utils/file.py
fastmindapi/utils/logging.py
fastmindapi/utils/transform.py
fastmindapi-0.0.9.dist-info/LICENSE
fastmindapi-0.0.9.dist-info/METADATA
fastmindapi-0.0.9.dist-info/WHEEL
fastmindapi-0.0.9.dist-info/entry_points.txt
fastmindapi-0.0.9.dist-info/top_level.txt
fastmindapi-0.0.9.dist-info/RECORD
