Metadata-Version: 2.1
Name: fastmindapi
Version: 0.0.9
Summary: An easy-to-use, high-performance(?) backend for serving LLMs and other AI models, built on FastAPI.
Author-email: Mengsong Wu <radi.cat@qq.com>
Maintainer-email: Mengsong Wu <radi.cat@qq.com>
License: Apache License
Project-URL: Homepage, https://github.com/fairyshine/FastMindAPI/
Project-URL: Bug Tracker, https://github.com/fairyshine/FastMindAPI/issues
Project-URL: Source, https://github.com/fairyshine/FastMindAPI
Requires-Python: >=3.10
License-File: LICENSE
Requires-Dist: pydantic
Requires-Dist: uvicorn
Requires-Dist: fastapi
Requires-Dist: rich
